{
    "configurations": [
        {
            "name": "Win32",
            "includePath": [
                "${workspaceFolder}/**",
                "D:/SET/mingw64/bin/../lib/gcc/x86_64-w64-mingw32/13.2.0/include/c++",
                "D:/SET/mingw64/bin/../lib/gcc/x86_64-w64-mingw32/13.2.0/include/c++/x86_64-w64-mingw32",
                "D:/SET/mingw64/bin/../lib/gcc/x86_64-w64-mingw32/13.2.0/include/c++/backward",
                "D:/SET/mingw64/bin/../lib/gcc/x86_64-w64-mingw32/13.2.0/include",
                "D:/SET/mingw64/bin/../lib/gcc/x86_64-w64-mingw32/13.2.0/include-fixed",
                "D:/SET/mingw64/bin/../lib/gcc/x86_64-w64-mingw32/13.2.0/../../../../x86_64-w64-mingw32/include"

            ],
            "defines": [
                "_DEBUG",
                "UNICODE",
                "_UNICODE"
            ],
            "compilerPath": "D:\\SET\\mingw64\\bin\\gcc.exe",
            "cStandard": "c17",
            "cppStandard": "gnu++17",
            "intelliSenseMode": "windows-gcc-x64"
        }
    ],
    "version": 4
}